<core:FragmentDefinition
	xmlns="sap.m"
	xmlns:core="sap.ui.core"
	xmlns:l="sap.ui.layout"
>
	<Popover
		showHeader="false"
		contentWidth="270px"
		contentHeight="340px"
		placement="Right"
	>
		<NavContainer id="baserentnv">	
            <Page
				title="Change - {i18n>Contract.BaseRent}"
				id="baserentchg"
			>
				<HBox
					alignContent="SpaceBetween"
					alignItems="Stretch"
					width="100%"
				>
                <l:VerticalLayout
						class="sapUiContentPadding"
						width="100%"
					>
						<l:content>
                        <Label
								design="Bold"
								text="{i18n>Label.Yr1} :"
							/>
							<Input
								autocomplete="false"
								description="{Term1/Currency}"
								fieldWidth="4rem"
								value="{
                                    parts: [{
									            path: 'Term1/Baserentyr1'
								            },
                                            {
									            path: 'Term1/Currency'
								            }],
									        type: 'sap.ui.model.type.Currency',
									        formatOptions: {
									            showMeasure: false
								}}"
							/>    
                              <Label
								design="Bold"
								text="{i18n>Label.Yr2} :"
							/>
							<Input
								autocomplete="false"
								description="{Term1/Currency}"
								fieldWidth="4rem"
								value="{
                                    parts: [{
									            path: 'Term1/Baserentyr2'
								            },
                                            {
									            path: 'Term1/Currency'
								            }],
									        type: 'sap.ui.model.type.Currency',
									        formatOptions: {
									            showMeasure: false
								}}"
							/>    
                              <Label
								design="Bold"
								text="{i18n>Label.Yr3} :"
							/>
							<Input
								autocomplete="false"
								description="{Term1/Currency}"
								fieldWidth="4rem"
								value="{
                                    parts: [{
									            path: 'Term1/Baserentyr3'
								            },
                                            {
									            path: 'Term1/Currency'
								            }],
									        type: 'sap.ui.model.type.Currency',
									        formatOptions: {
									            showMeasure: false
								}}"
							/>    
                        </l:content>
                    </l:VerticalLayout>
                     <l:VerticalLayout
						class="sapUiContentPadding"
						width="100%"
					>
						<l:content>
                        <Label
								design="Bold"
								text="{i18n>Label.Yr4} :"
							/>
							<Input
								autocomplete="false"
								description="{Term1/Currency}"
								fieldWidth="4rem"
								value="{
                                    parts: [{
									            path: 'Term1/Baserentyr4'
								            },
                                            {
									            path: 'Term1/Currency'
								            }],
									        type: 'sap.ui.model.type.Currency',
									        formatOptions: {
									            showMeasure: false
								}}"
							/>    
                              <Label
								design="Bold"
								text="{i18n>Label.Yr5} :"
							/>
							<Input
								autocomplete="false"
								description="{Term1/Currency}"
								fieldWidth="4rem"
								value="{
                                    parts: [{
									            path: 'Term1/Baserentyr5'
								            },
                                            {
									            path: 'Term1/Currency'
								            }],
									        type: 'sap.ui.model.type.Currency',
									        formatOptions: {
									            showMeasure: false
								}}"
							/>    
                              <Label
								design="Bold"
								text="{i18n>Label.Yr6} :"
							/>
							<Input
								autocomplete="false"
								description="{Term1/Currency}"
								fieldWidth="4rem"
								value="{
                                    parts: [{
									            path: 'Term1/Baserentyr6'
								            },
                                            {
									            path: 'Term1/Currency'
								            }],
									        type: 'sap.ui.model.type.Currency',
									        formatOptions: {
									            showMeasure: false
								}}"
							/>    
                        </l:content>
                    </l:VerticalLayout>
                </HBox>
            </Page>
		</NavContainer>
	</Popover>
</core:FragmentDefinition>